{"medicamento":{"idDroga":"78","principioAtivoDroga":"CALCITRIOL","grupoFarmacoterapeutico":"VITAMINA D E ANÁLOGOS","nomeComercialDroga":"CALCIJEX; OSTRIOL; SIGMATRIOL; ROCALTROL","listaFtn":"N","listaMedSUS":"S","disponivelFarmaciaPopularRedePropria":"","disponivelFarmaciaPopularRedeParticular":"","apresentacao":"Cápsulas 0,25 mcg e 1 mcg","indicacao":"Para apresentação de 0,25 mcg:\nE200 - Hipoparatireoidismo idiopático\nE201 - Pseudohipoparatireoidismo\nE208 - Outro hipoparatireoidismo\nE892 - Hipoparatireoidismo pós-procedimento\nVer PCDT de Hipoparatiroidismo.\n\nE550 - Raquitismo ativo\nE559 - Deficiência não especificada de vitamina D\nE643 - Seqüelas do raquitismo\nE833 - Distúrbios do metabolismo do fósforo\nM830 - Osteomalácia puerperal\nM831 - Osteomalácia senil\nM832 - Osteomalácia do adulto devida a má-absorção\nM833 - Osteomalácia do adulto devido à desnutrição\nM838 - Outra osteomalácia do adulto\nVer PCDT de Raquitismo e Osteomalácia.\n\nM805 - Osteoporose idiopática com fratura patológica\nM815 - Osteoporose idiopática\nVer PCDT de Osteoporose.\n\nN180 - Doença renal em estádio final\nN188 - Outra insuficiência renal crônica\nN250 - Osteodistrofia renal\nN258 - Outros transtornos resultantes de função renal tubular alterada\nVer PCDT de Osteodistrofia Renal.\n\nPara apresentação de 1 mcg:\nN180 - Doença renal em estádio final\nN188 - Outra insuficiência renal crônica\nN250 - Osteodistrofia renal\nN258 - Outros transtornos resultantes de função renal tubular alterada\nVer PCDT de Osteodistrofia Renal.","contraIndicacao":"","precaucao":"","esquemaAdministracaoCrianca":"","esquemaAdministracaoAdulto":"","esquemaAdministracaoGestante":"","esquemaAdministracaoIdoso":"","aspectoFarmacocinetico":"","efeitoAdverso":"","interacaoMedicamentosa":"","informacaoPaciente":"","aspectoFarmaceutico":""}}